redcap_toolbox/__init__.py
redcap_toolbox/download_redcap.py
redcap_toolbox/download_redcap_report.py
redcap_toolbox/minchange.py
redcap_toolbox/split_redcap_data.py
redcap_toolbox/update_redcap_diff.py
redcap_toolbox-2025.9.10.dist-info/METADATA
redcap_toolbox-2025.9.10.dist-info/WHEEL
redcap_toolbox-2025.9.10.dist-info/entry_points.txt
redcap_toolbox-2025.9.10.dist-info/licenses/LICENSE
redcap_toolbox-2025.9.10.dist-info/RECORD
