Metadata-Version: 2.4
Name: redcap_toolbox
Version: 2025.9.10
Summary: A collection of tools to interact with the REDCap API
Project-URL: Homepage, https://github.com/uwmadison-chm/redcap-toolbox
Project-URL: Issues, https://github.com/uwmadison-chm/redcap-toolbox/issues
Author-email: Nate Vack <njvack@wisc.edu>
Maintainer-email: Nate Vack <njvack@wisc.edu>, Nicholas Vanhaute <nvanhaute@wisc.edu>, Stuti Shrivastava <sshrivastav6@wisc.edu>
License-File: LICENSE
Classifier: Development Status :: 5 - Production/Stable
Classifier: Intended Audience :: Science/Research
Classifier: License :: OSI Approved :: MIT License
Classifier: Natural Language :: English
Classifier: Operating System :: OS Independent
Classifier: Programming Language :: Python :: 3
Requires-Python: >=3.9
Requires-Dist: docopt-ng>=0.9.0
Requires-Dist: pandas>=2.2.3
Requires-Dist: pycap>=2.7.0
